aivk_qq/__about__.py
aivk_qq/__init__.py
aivk_qq/py.typed
aivk_qq/base/enums.py
aivk_qq/base/message.py
aivk_qq/base/models.py
aivk_qq/base/utils.py
aivk_qq/cli/__init__.py
aivk_qq/cli/__main__.py
aivk_qq/mcp/__init__.py
aivk_qq/mcp/__main__.py
aivk_qq/mcp/server.py
aivk_qq/napcat/api.py
aivk_qq/napcat/client.py
aivk_qq-0.1.3.0.dist-info/METADATA
aivk_qq-0.1.3.0.dist-info/WHEEL
aivk_qq-0.1.3.0.dist-info/entry_points.txt
aivk_qq-0.1.3.0.dist-info/licenses/LICENSE
aivk_qq-0.1.3.0.dist-info/RECORD
