Metadata-Version: 2.4
Name: aivk_qq
Version: 0.1.3.0
Summary: AIVK-QQ：一个强大的QQ机器人框架，集成MCP服务器、CLI工具、Napcat.Shell启动器和Napcat API SDK于一体，为AI驱动的QQ交互提供全方位支持
Author-email: LIghtJUNction <lightjunction.me@gmail.com>
License-File: LICENSE
Requires-Python: >=3.13
Requires-Dist: aivk>=0.3.2.20
Requires-Dist: click>=8.1.8
Requires-Dist: httpx>=0.28.1
Requires-Dist: mcp[cli]>=1.6.0
Requires-Dist: tqdm>=4.67.1
Requires-Dist: websockets>=15.0.1
